Workbook

Sheet Summary
A1: AtliQ Contract IQ — Cost Estimation Summary
A2: Editable planning model for a contract-review MVP. Cost outputs are formula-linked to Volume Sizing, Inference, and Infrastructure.
A4: Cost line | B4: Model / service | C4: Estimated monthly cost | D4: Notes
A5: F1 Contract intake and triage | B5: Groq GPT-OSS 20B | C5: ='Inference (Groq)'!J10 | D5: Classifies document type and extracts intake metadata.
A6: F2 Clause extraction | B6: Groq GPT-OSS 120B | C6: ='Inference (Groq)'!J11 | D6: Extracts material clauses from contract chunks.
A7: F3 Checklist and precedent comparison | B7: Groq GPT-OSS 120B | C7: ='Inference (Groq)'!J12 | D7: Compares extracted terms with checklist and historical records.
A8: F4 Prioritized risk report | B8: Groq GPT-OSS 120B | C8: ='Inference (Groq)'!J13 | D8: Creates evidence-backed findings for human review.
A9: Retry and evaluation buffer | B9: 25% of AI inference | C9: ='Inference (Groq)'!J16 | D9: Covers retries, prompt growth, and limited evaluation runs.
A10: AI inference subtotal | B10: Groq API | C10: ='Inference (Groq)'!J17 | D10: Variable cost; depends on document length and model usage.
A11: Application hosting | B11: Vercel Pro (planning assumption) | C11: 20 | D11: Confirm current plan/pricing and production needs.
A12: Database and audit storage | B12: Supabase Pro (planning assumption) | C12: 25 | D12: Confirm current plan/pricing, retention, and storage needs.
A13: OCR | B13: Deferred / not included | C13: 0 | D13: Add only if scanned/image-based contracts are in scope.
A14: Embeddings | B14: Optional; excluded from base case | C14: 0 | D14: Add if semantic retrieval is implemented.
A15: Estimated MVP total per month | B15: AI + hosting + database | C15: =SUM(C10:C14) | D15: Before taxes, labour, OCR, and other add-ons.
A16: Contracts reviewed per month | B16: Volume Sizing | C16: ='Volume Sizing'!C5 | D16: Editable volume assumption.
A17: AI cost per contract | B17: AI subtotal ÷ contracts | C17: =C10/C16 | D17: Variable inference cost per contract.
A18: Blended operating cost per contract | B18: Monthly total ÷ contracts | C18: =C15/C16 | D18: Includes shared hosting and database costs.
A21: Important note | B21: All workload, token, and savings figures are planning assumptions until measured. Verify current Groq and infrastructure pricing before relying on totals.

Sheet Volume Sizing
A1: AtliQ Contract IQ — Volume Sizing
A2: Yellow cells are editable planning assumptions. Replace them with measured workload and prototype logs when available.
A4: Measure | B4: Dataset / current evidence | C4: Base-case assumption | D4: How it is scaled / notes
A5: Contract tracker rows | B5: 48 rows supplied | C5: 48 | D5: Tracker rows are not necessarily unique, complete contracts; includes a duplicate Northwind SOW record.
A6: Contracts reviewed per month | B6: Not established | C6: 50 | D6: Planning assumption only; replace with observed or expected monthly contract review volume.
A7: Average pages per contract | B7: Not measured | C7: 20 | D7: Assumed average across MSAs, SOWs, NDAs, and contractor agreements.
A8: Average words per page | B8: Not measured | C8: 500 | D8: Working assumption for text-heavy contracts.
A9: Average words per contract | B9: Formula | C9: =C6*C7 | D9: Average pages × average words per page.
A10: GPT-OSS tokens per word | B10: Sample assumption | C10: 1.3 | D10: Reuses the supplied sample's 1.3 tokens/word assumption; actual tokenization may vary.
A11: Source tokens per contract | B11: Formula | C11: =C8*C9 | D11: Average words per contract × tokens per word.
A12: Total pages per month | B12: Formula | C12: =C5*C6 | D12: Contracts reviewed × average pages.
A13: Total source words per month | B13: Formula | C13: =C5*C8 | D13: Contracts reviewed × average words per contract.
A14: Total source tokens per month | B14: Formula | C14: =C5*C10 | D14: Contracts reviewed × source tokens per contract.
A15: Intake calls per contract | B15: Planning assumption | C15: 1 | D15: One intake / triage call per contract.
A16: Extraction chunks per contract | B16: Planning assumption | C16: 10 | D16: Assumes each 20-page contract is processed in 10 chunks; validate against the implementation.
A17: Precedent comparison calls per contract | B17: Planning assumption | C17: 1 | D17: One comparison pass over extracted clauses and relevant historical material.
A18: Final report calls per contract | B18: Planning assumption | C18: 1 | D18: One final prioritized risk report per contract.
A19: Total model calls per contract | B19: Formula | C19: =C15+C16+C17+C18 | D19: Sum of intake, extraction chunks, precedent comparison, and report calls.
A20: Total intake calls per month | B20: Formula | C20: =C5*C15 | D20: Contracts × intake calls per contract.
A21: Total extraction calls per month | B21: Formula | C21: =C5*C16 | D21: Contracts × extraction chunks per contract.
A22: Total precedent calls per month | B22: Formula | C22: =C5*C17 | D22: Contracts × comparison calls per contract.
A23: Total report calls per month | B23: Formula | C23: =C5*C18 | D23: Contracts × report calls per contract.
A24: Total model calls per month | B24: Formula | C24: =SUM(C20:C23) | D24: Total calls across the four workflow stages.

Sheet Inference (Groq)
A1: AtliQ Contract IQ — Groq Inference Cost
A2: Rates are taken from the supplied sample's rate card and must be rechecked before use. Yellow cells are assumptions; model-token estimates are not measured.
A4: Model / pricing item | B4: Input $ / 1M tokens | C4: Cached input $ / 1M | D4: Output $ / 1M tokens | E4: Notes
A5: openai/gpt-oss-20b | B5: 0.075 | C5: 0.0375 | D5: 0.3 | E5: Sample rate card; confirm current Groq pricing.
A6: openai/gpt-oss-120b | B6: 0.15 | C6: 0.075 | D6: 0.6 | E6: Sample rate card; confirm current Groq pricing.
A9: Task | B9: Model | C9: Calls / month | D9: Input tokens / call | E9: Cacheable prefix tokens | F9: Cache-hit rate | G9: Visible output tokens | H9: Reasoning allowance tokens | I9: Cost / call | J9: Cost / month | K9: Notes
A10: F1 Contract intake and triage | B10: 20B | C10: ='Volume Sizing'!C20 | D10: 15000 | E10: 3000 | F10: 0.5 | G10: 400 | H10: 300 | I10: =(((E10*F10)*INDEX($C$5:$C$6,IF(B10="20B",5,6))+(D10-E10*F10)*INDEX($B$5:$B$6,IF(B10="20B",5,6)))/1000000)+((G10+H10)*INDEX($D$5:$D$6,IF(B10="20B",5,6))/1000000) | J10: =C10*I10 | K10: One intake call per contract; assumed token counts.
A11: F2 Clause extraction | B11: 120B | C11: ='Volume Sizing'!C21 | D11: 3500 | E11: 1000 | F11: 0.5 | G11: 700 | H11: 500 | I11: =(((E11*F11)*INDEX($C$5:$C$6,IF(B11="20B",5,6))+(D11-E11*F11)*INDEX($B$5:$B$6,IF(B11="20B",5,6)))/1000000)+((G11+H11)*INDEX($D$5:$D$6,IF(B11="20B",5,6))/1000000) | J11: =C11*I11 | K11: 10 extraction chunks per contract; includes chunk text and prompt.
A12: F3 Checklist and precedent comparison | B12: 120B | C12: ='Volume Sizing'!C22 | D12: 8000 | E12: 2500 | F12: 0.5 | G12: 1200 | H12: 800 | I12: =(((E12*F12)*INDEX($C$5:$C$6,IF(B12="20B",5,6))+(D12-E12*F12)*INDEX($B$5:$B$6,IF(B12="20B",5,6)))/1000000)+((G12+H12)*INDEX($D$5:$D$6,IF(B12="20B",5,6))/1000000) | J12: =C12*I12 | K12: Assumes relevant precedent snippets are supplied in context.
A13: F4 Prioritized risk report | B13: 120B | C13: ='Volume Sizing'!C23 | D13: 3000 | E13: 1500 | F13: 0.5 | G13: 1200 | H13: 500 | I13: =(((E13*F13)*INDEX($C$5:$C$6,IF(B13="20B",5,6))+(D13-E13*F13)*INDEX($B$5:$B$6,IF(B13="20B",5,6)))/1000000)+((G13+H13)*INDEX($D$5:$D$6,IF(B13="20B",5,6))/1000000) | J13: =C13*I13 | K13: Outputs evidence-linked findings and next actions for human review.
A15: Inference subtotal | J15: =SUM(J10:J13)
A16: Retry/evaluation buffer | C16: 0.25 | J16: =J15*C16
A17: Estimated AI total / month | J17: =J15+J16
A18: Estimated AI cost / contract | J18: =J17/'Volume Sizing'!C5
A21: Formula note: cost/call = standard input + estimated cached input discount + (visible output + reasoning allowance) at the selected model's output rate. Cache assumptions must be replaced with measured cache behavior.

Sheet Infrastructure
A1: AtliQ Contract IQ — Infrastructure Estimate
A2: Planning estimates only. Verify current provider plans, data handling, and retention/security requirements before processing confidential contracts.
A4: Component | B4: Assumption / service | C4: Monthly estimate | D4: Notes / validation
A5: Application hosting | B5: Vercel Pro | C5: 20 | D5: Budget placeholder; verify current plan and deployment needs.
A6: Database and audit records | B6: Supabase Pro | C6: 25 | D6: Budget placeholder; verify current price, storage, backups, and retention.
A7: Document storage | B7: Included / low initial volume | C7: 0 | D7: Confirm whether the selected plan covers original files and derived artifacts.
A8: OCR | B8: Out of MVP scope | C8: 0 | D8: Add a separate estimate if scanned PDFs are included.
A9: Monitoring / error tracking | B9: Free tier initially | C9: 0 | D9: Reassess before production rollout.
A10: Embeddings / vector store | B10: Not used in base case | C10: 0 | D10: Optional; estimate if semantic retrieval is implemented.
A12: Estimated infrastructure total | C12: =SUM(C5:C10)

Sheet Embeddings
A1: AtliQ Contract IQ — Embeddings Decision
A2: Embeddings are optional; do not charge for them unless the prototype actually uses semantic retrieval.
A4: Item | B4: Base-case decision | C4: Estimate | D4: Notes
A5: Semantic retrieval | B5: Deferred / not used | C5: $0.00 | D5: Use deterministic filtering and keyword search over curated historical agreements and negotiation notes for MVP.
A6: When to add | B6: If keyword retrieval misses relevant precedents | C6: TBD | D6: Evaluate retrieval quality using labelled precedent queries.
A7: Cost drivers | B7: Embedding input tokens; indexing refresh; vector storage; retrieval service | C7: TBD | D7: Measure corpus size, re-indexing frequency, and monthly queries before pricing.
A8: Safety requirement | B8: Human verification of retrieved precedent | C8: Required | D8: Historical notes can be incomplete or exceptions; do not treat as authoritative policy without validation.

Sheet Cost Savings
A1: AtliQ Contract IQ — Cost Savings Model
A2: Editable assumptions. Include human verification time in AI-assisted review time; savings are potential capacity value, not guaranteed cash savings.
A4: Measure | B4: Value | C4: Unit / formula | D4: Notes
A5: Contracts reviewed per month | B5: ='Volume Sizing'!C5 | C5: contracts | D5: Linked to volume sizing.
A6: Manual review time per contract | B6: 120 | C6: minutes | D6: Illustrative assumption; replace with measured baseline.
A7: AI-assisted review time per contract | B7: 75 | C7: minutes | D7: Illustrative assumption including human verification.
A8: Reviewer hourly cost | B8: 50 | C8: USD/hour | D8: Illustrative assumption; replace with AtliQ's fully loaded rate.
A9: Hours saved per month | B9: =B5*(B6-B7)/60 | C9: hours | D9: Contracts × (manual minutes − AI-assisted minutes) ÷ 60.
A10: Potential value of time saved | B10: =B9*B8 | C10: USD/month | D10: Capacity value; not necessarily cash savings.
A11: Estimated monthly operating cost | B11: =Summary!C15 | C11: USD/month | D11: Linked to Summary.
A12: Estimated net monthly benefit | B12: =B10-B11 | C12: USD/month | D12: Potential value minus operating cost; sensitive to time-saving assumptions.

Sheet Sources & Assumptions
A1: AtliQ Contract IQ — Sources & Assumptions
A2: Separate project facts from planning assumptions and measured prototype values. Verify external prices and security terms before launch.
A4: Type | B4: Source / assumption | C4: Treatment / next action
A5: Project fact | B5: Supplied contract tracker: 48 rows | C5: Does not establish 48 unique or complete contracts; includes duplicate/missing metadata.
A6: Project fact | B6: AtliQ entities and contract checklist | C6: Use entity rules and checklist as supplied; confirm exceptions with authorized reviewer.
A7: Project fact | B7: Historical negotiation notes | C7: Some notes are reconstructed or incomplete; label as precedent, exception, rejected position, or unverified.
A8: Planning assumption | B8: 50 contracts/month; 20 pages/contract; 500 words/page | C8: Replace with measured expected volume and representative contract lengths.
A9: Planning assumption | B9: 1.30 GPT-OSS tokens per English word | C9: Approximation; measure token counts in prototype logs.
A10: Planning assumption | B10: 10 extraction chunks per contract | C10: Validate chunk size, overlap, prompt overhead, and model limits.
A11: Pricing assumption | B11: Groq model prices copied from supplied sample | C11: Recheck current official Groq pricing and cache behavior before final submission.
A12: Infrastructure assumption | B12: Vercel Pro $20/month; Supabase Pro $25/month | C12: Budget placeholders; verify current pricing, storage, retention, and required features.
A13: Excluded | B13: OCR, legal research database, engineering labour, taxes, enterprise integrations | C13: Add if these become part of MVP or production scope.
A14: Security gate | B14: Provider retention, data residency, approved services, access control | C14: Confirm before processing confidential real contracts; low inference cost does not establish compliance.
A15: Measured values | B15: No prototype usage logs entered yet | C15: Replace assumptions with actual token usage, call counts, retries, and costs after running tests.
